bmoney/cli.py
bmoney/constants.py
bmoney/app/app.py
bmoney/utils/config.py
bmoney/utils/data.py
bmoney/utils/deduplication.py
bmoney/utils/gcloud.py
bmoney-0.4.3.dist-info/METADATA
bmoney-0.4.3.dist-info/WHEEL
bmoney-0.4.3.dist-info/entry_points.txt
bmoney-0.4.3.dist-info/licenses/LICENSE
bmoney-0.4.3.dist-info/RECORD
