Metadata-Version: 2.4
Name: bmoney
Version: 0.4.3
Summary: Budget Money - powerful budgeting tools extending Rocket Money transaction exports
Project-URL: Homepage, https://github.com/dskarbrevik/budget-money
Project-URL: Issues, https://github.com/dskarbrevik/budget-money/issues
Author: David Skarbrevik
License-Expression: MIT
License-File: LICENSE
Requires-Python: <3.14,>=3.10
Requires-Dist: google-api-core>=2.24.0
Requires-Dist: google-api-python-client>=2.158.0
Requires-Dist: google-auth-httplib2>=0.2.0
Requires-Dist: google-auth-oauthlib>=1.2.1
Requires-Dist: google-auth>=2.37.0
Requires-Dist: matplotlib>=3.10.0
Requires-Dist: pandas>=2.2.3
Requires-Dist: plotly>=5.24.1
Requires-Dist: python-dotenv>=1.0.1
Requires-Dist: streamlit>=1.41.1
Requires-Dist: typer>=0.15.1
